dcm2niix_webui/__init__.py
dcm2niix_webui/gradio_interfaces.py
dcm2niix_webui/main.py
dcm2niix_webui/resources/image/example_dicom_dir.jpg
dcm2niix_webui/resources/image/example_dicom_zip.jpg
dcm2niix_webui/util/__init__.py
dcm2niix_webui/util/lib_SimpleITK.py
dcm2niix_webui/util/lib_common.py
dcm2niix_webui/util/lib_dcm2nii.py
dcm2niix_webui-0.1.2.dist-info/LICENSE
dcm2niix_webui-0.1.2.dist-info/METADATA
dcm2niix_webui-0.1.2.dist-info/WHEEL
dcm2niix_webui-0.1.2.dist-info/entry_points.txt
dcm2niix_webui-0.1.2.dist-info/top_level.txt
dcm2niix_webui-0.1.2.dist-info/RECORD
