Metadata-Version: 2.1
Name: dcm2niix-webui
Version: 0.1.2
Summary: The web UI for dcm2niix (DICOM to NIfTI converter)
Author-email: Lion A <alionsss@foxmail.com>
License: License :: OSI Approved :: Apache Software License
Project-URL: Homepage, https://github.com/AlionSSS/dcm2niix-webui
Project-URL: Repository, https://github.com/AlionSSS/dcm2niix-webui.git
Keywords: dcm2niix,ui,webui,medicine,dicom,dcm,nii,research
Classifier: Development Status :: 4 - Beta
Classifier: License :: OSI Approved :: Apache Software License
Classifier: Intended Audience :: Education
Classifier: Intended Audience :: Healthcare Industry
Classifier: Intended Audience :: Science/Research
Classifier: Operating System :: Microsoft :: Windows
Classifier: Operating System :: POSIX :: Linux
Classifier: Programming Language :: Python :: 3
Classifier: Programming Language :: Python :: 3.10
Classifier: Topic :: Scientific/Engineering :: Medical Science Apps.
Requires-Python: >=3.6
License-File: LICENSE
Requires-Dist: gradio ==4.29
Requires-Dist: dcm2niix
